{"cameraMode":{"drawMode":0,"name":"Shaded","section":"Shading Mode"},"sceneLighting":false,"audioPlay":false,"sceneViewState":{"showFog":true,"showMaterialUpdate":false,"showSkybox":false,"showFlares":true,"showImageEffects":true,"showParticleSystems":true},"in2DMode":false,"pivot":{"x":-3.063047409057617,"y":0.9999999403953552,"z":-3.340160846710205},"rotation":{"x":0.041181646287441257,"y":-0.9587465524673462,"z":0.20524975657463075,"w":0.1923491358757019},"size":1.5494416952133179,"orthographic":false}